stream_read_xbrl.py
stream_read_xbrl-0.0.47.dist-info/METADATA
stream_read_xbrl-0.0.47.dist-info/WHEEL
stream_read_xbrl-0.0.47.dist-info/licenses/LICENSE
stream_read_xbrl-0.0.47.dist-info/RECORD
